qubo/__init__.py
qubo/qubo.py
qubo-0.0.1.dist-info/LICENSE
qubo-0.0.1.dist-info/METADATA
qubo-0.0.1.dist-info/WHEEL
qubo-0.0.1.dist-info/top_level.txt
qubo-0.0.1.dist-info/RECORD
